Metadata-Version: 1.0
Name: swift-cloud
Version: 0.2.18
Summary: Middleware for Openstack Swift to store objecs on multiple cloud providers
Home-page: UNKNOWN
Author: Storm
Author-email: storm@g.globo
License: UNKNOWN
Platform: UNKNOWN
